textparsingtools.py
textparsingtools-1.1.6.dist-info/LICENSE
textparsingtools-1.1.6.dist-info/METADATA
textparsingtools-1.1.6.dist-info/WHEEL
textparsingtools-1.1.6.dist-info/top_level.txt
textparsingtools-1.1.6.dist-info/RECORD
