Metadata-Version: 2.1
Name: textparsingtools
Version: 1.1.6
Summary: A collection of methods to read and organize data stored in text
Home-page: UNKNOWN
Author: Reid Prichard
Author-email: rprichard@liberty.edu
License: MIT
Platform: UNKNOWN
Classifier: License :: OSI Approved :: MIT License
Classifier: Programming Language :: Python :: 3.8
Requires-Dist: xlsxwriter
